README.rst
setup.py
bets/__init__.py
bets_api.egg-info/PKG-INFO
bets_api.egg-info/SOURCES.txt
bets_api.egg-info/dependency_links.txt
bets_api.egg-info/requires.txt
bets_api.egg-info/top_level.txt