Metadata-Version: 1.1
Name: bets-api
Version: 0.0.7
Summary: A wrapper over bets.42cc.co API
Home-page: https://github.com/42cc/bets-api
Author: 42 Coffee Cups
Author-email: contact@42cc.co
License: GPL v2 License
Download-URL: https://github.com/42cc/bets-api/archive/master.zip
Keywords: bets,api
Platform: UNKNOWN
Classifier: Environment :: Web Environment
Classifier: Intended Audience :: Developers
Classifier: License :: OSI Approved :: GNU General Public License v2 (GPLv2)
Classifier: Programming Language :: Python
Requires: python (>= 2.7)
